mlcpl/__init__.py
mlcpl/helper.py
mlcpl/label_strategies.py
mlcpl/pseudo_labeling.py
mlcpl/augs/__init__.py
mlcpl/augs/logic_mix.py
mlcpl/augs/mixup_pme.py
mlcpl/cft/__init__.py
mlcpl/cft/core.py
mlcpl/cft/optimization_method.py
mlcpl/datasets/__init__.py
mlcpl/datasets/core.py
mlcpl/datasets/loaders.py
mlcpl/losses/__init__.py
mlcpl/losses/focal_losses.py
mlcpl/losses/large_loss_matters.py
mlcpl/losses/strictly_proper_asymmetric_loss.py
mlcpl/metrics/__init__.py
mlcpl/metrics/calibration_error.py
mlcpl/metrics/core.py
mlcpl/metrics/functional.py
mlcpl/metrics/module.py
mlcpl-0.1.7.dist-info/METADATA
mlcpl-0.1.7.dist-info/WHEEL
mlcpl-0.1.7.dist-info/licenses/LICENSE
mlcpl-0.1.7.dist-info/RECORD
