Metadata-Version: 2.4
Name: mlcpl
Version: 0.1.7
Summary: Add your description here
License-File: LICENSE
Requires-Python: >=3.8
Requires-Dist: cython>=0.29.33
Requires-Dist: lvis>=0.5.3
Requires-Dist: pandas>=2.0
Requires-Dist: protobuf>=3.20.1
Requires-Dist: pycocotools>=2.0.7
Requires-Dist: tensorboard>=2.14.0
Requires-Dist: torch>=1.13.1
Requires-Dist: torchmetrics>=1.5.2
Requires-Dist: torchvision>=0.14.1
Requires-Dist: xmltodict>=0.13.0
